Metadata-Version: 2.1
Name: edutorch
Version: 0.0.3
Summary: Rewritten PyTorch framework designed to help you learn AI/ML
Home-page: https://github.com/tyleryep/edutorch
Author: Tyler Yep
Author-email: tyep10@gmail.com
License: UNKNOWN
Platform: UNKNOWN
Classifier: Programming Language :: Python :: 3
Classifier: License :: OSI Approved :: MIT License
Classifier: Operating System :: OS Independent
Requires-Python: >=3.7
